simtester/__init__.py
simtester/agent/__init__.py
simtester/agent/agent.py
simtester/agent/multiwoz_agent/__init__.py
simtester/agent/multiwoz_agent/multiwoz_agent.py
simtester/config/__init__.py
simtester/config/multiwoz/__init__.py
simtester/config/multiwoz/config.py
simtester/config/multiwoz/mapping.py
simtester/tester/__init__.py
simtester/tester/tester.py
simtester/utils/__init__.py
simtester/utils/utils.py
simtester/utils/multiwoz/__init__.py
simtester/utils/multiwoz/delexicalize.py
simtester/utils/multiwoz/evaluate.py
simtester/utils/multiwoz/nlp.py
simtester/utils/multiwoz/utils.py
simtester-0.1.0.dist-info/METADATA
simtester-0.1.0.dist-info/WHEEL
simtester-0.1.0.dist-info/top_level.txt
simtester-0.1.0.dist-info/RECORD
