Metadata-Version: 2.1
Name: simtester
Version: 0.1.0
Summary: An Open-Source Toolkit for Evaluating User Simulator of Task-oriented Dialogue System
Home-page: https://github.com/Superbooming/simtester
Author: shuyu guo
Author-email: guoshuyu225@gmail.com
License: UNKNOWN
Platform: UNKNOWN
Classifier: Programming Language :: Python :: 3
Classifier: License :: OSI Approved :: MIT License
Classifier: Topic :: Scientific/Engineering :: Artificial Intelligence
Classifier: Topic :: Scientific/Engineering :: Human Machine Interfaces
Requires-Python: >=3.6
Requires-Dist: loguru (~=0.6.0)
Requires-Dist: transformers (~=4.12.5)
Requires-Dist: pyyaml (~=6.0)
Requires-Dist: tqdm (~=4.55.0)
Requires-Dist: nltk (~=3.4.5)
Requires-Dist: requests (~=2.25.1)
